aionostr/__init__.py
aionostr/bech32.py
aionostr/benchmark.py
aionostr/cli.py
aionostr/delegation.py
aionostr/event.py
aionostr/key.py
aionostr/relay.py
aionostr/util.py
electrum_aionostr-0.0.1.dist-info/AUTHORS.rst
electrum_aionostr-0.0.1.dist-info/LICENSE
electrum_aionostr-0.0.1.dist-info/METADATA
electrum_aionostr-0.0.1.dist-info/WHEEL
electrum_aionostr-0.0.1.dist-info/entry_points.txt
electrum_aionostr-0.0.1.dist-info/top_level.txt
electrum_aionostr-0.0.1.dist-info/RECORD
