Metadata-Version: 2.1
Name: electrum-aionostr
Version: 0.0.1
Summary: asyncio nostr client
Home-page: https://github.com/spesmilo/electrum-aionostr
Author: Dave St.Germain
Author-email: dave@st.germa.in
License: BSD license
Keywords: aionostr
Classifier: Development Status :: 2 - Pre-Alpha
Classifier: Intended Audience :: Developers
Classifier: License :: OSI Approved :: BSD License
Classifier: Natural Language :: English
Classifier: Programming Language :: Python :: 3
Classifier: Programming Language :: Python :: 3.8
Classifier: Programming Language :: Python :: 3.9
Classifier: Programming Language :: Python :: 3.10
Classifier: Programming Language :: Python :: 3.11
Classifier: Programming Language :: Python :: 3.12
Requires-Python: >=3.8
License-File: LICENSE
License-File: AUTHORS.rst
Requires-Dist: electrum-ecc
Requires-Dist: websockets
Requires-Dist: cryptography >=37.0.4
